engrave/__init__.py
engrave/error.html
engrave/main.py
engrave/server.py
engrave/template.py
engrave/core/build.py
engrave/core/cli.py
engrave/core/watch.py
engrave/util/dataclass.py
engrave/util/log.py
engrave/util/process.py
engrave-3.1.5.dist-info/METADATA
engrave-3.1.5.dist-info/WHEEL
engrave-3.1.5.dist-info/entry_points.txt
engrave-3.1.5.dist-info/licenses/LICENSE
engrave-3.1.5.dist-info/RECORD
