Metadata-Version: 2.4
Name: engrave
Version: 3.1.5
Summary: A static site generator with live preview capability
Author-email: Nitipit Nontasuwan <nitipit@gmail.com>
Maintainer-email: Nitipit Nontasuwan <nitipit@gmail.com>
License-Expression: MIT
License-File: LICENSE
Keywords: generator,preview,static site generator,template,web,website
Requires-Python: >=3.10
Requires-Dist: aiostream>=0.6.4
Requires-Dist: cyclopts>=3.11.2
Requires-Dist: dacite>=1.9.2
Requires-Dist: fastapi[standard]>=0.115.8
Requires-Dist: ipython>=8.37.0
Requires-Dist: jinja2>=3.1.5
Requires-Dist: markupsafe>=3.0.2
Requires-Dist: mistune>=3.1.2
Requires-Dist: uvicorn>=0.34.0
Requires-Dist: watchfiles>=1.0.4
